README.rst
setup.py
cobra/__init__.py
cobra/ast.py
cobra/base.py
cobra/compiler.py
cobra/translator.py
cobra/utils.py
cobrascript.egg-info/PKG-INFO
cobrascript.egg-info/SOURCES.txt
cobrascript.egg-info/dependency_links.txt
cobrascript.egg-info/entry_points.txt
cobrascript.egg-info/not-zip-safe
cobrascript.egg-info/top_level.txt