Metadata-Version: 1.1
Name: cobrascript
Version: 0.1.2
Summary: Python syntax translator to Javascript.
Home-page: https://github.com/niwibe/cobrascript
Author: Andrey Antukh
Author-email: niwi@niwi.be
License: BSD License
Platform: unix
Platform: linux
Platform: osx
Platform: cygwin
Platform: win32
Classifier: Development Status :: 3 - Alpha
Classifier: Intended Audience :: Developers
Classifier: Environment :: Console
Classifier: License :: OSI Approved :: BSD License
Classifier: Operating System :: POSIX
Classifier: Operating System :: Microsoft :: Windows
Classifier: Operating System :: MacOS :: MacOS X
Classifier: Topic :: Software Development :: Libraries
Classifier: Topic :: Utilities
Classifier: Programming Language :: Python :: 3
Classifier: Programming Language :: Python :: 3.3
